shamir_ss/__init__.py
shamir_ss/shamir.c
shamir_ss/shamir.cpython-313-darwin.so
shamir_ss/shamir.pyx
shamir_ss-0.1.0.dist-info/licenses/LICENCE
src/shamir.cpython-313-darwin.so
shamir_ss-0.1.0.dist-info/METADATA
shamir_ss-0.1.0.dist-info/WHEEL
shamir_ss-0.1.0.dist-info/top_level.txt
shamir_ss-0.1.0.dist-info/RECORD
